[
  {
    "1": 2,
    "Blue-eyes White Dragon": "Mystical Elf",
    "999.999": 160
  },
  {
    "1": 3,
    "Blue-eyes White Dragon": "Hitotsu-me Giant",
    "999.999": 70
  },
  {
    "1": 4,
    "Blue-eyes White Dragon": "Baby Dragon",
    "999.999": 999.999
  },
  {
    "1": 5,
    "Blue-eyes White Dragon": "Ryu-kishin",
    "999.999": 30
  },
  {
    "1": 6,
    "Blue-eyes White Dragon": "Feral Imp",
    "999.999": 140
  },
  {
    "1": 7,
    "Blue-eyes White Dragon": "Winged Dragon #1",
    "999.999": 999.999
  },
  {
    "1": 8,
    "Blue-eyes White Dragon": "Mushroom Man",
    "999.999": 30
  },
  {
    "1": 9,
    "Blue-eyes White Dragon": "Shadow Specter",
    "999.999": 15
  },
  {
    "1": 10,
    "Blue-eyes White Dragon": "Blackland Fire Dragon",
    "999.999": 80
  },
  {
    "1": 11,
    "Blue-eyes White Dragon": "Sword Arm of Dragon",
    "999.999": 1
  },
  {
    "1": 12,
    "Blue-eyes White Dragon": "Swamp Battleguard",
    "999.999": 290
  },
  {
    "1": 13,
    "Blue-eyes White Dragon": "Tyhone",
    "999.999": 120
  },
  {
    "1": 14,
    "Blue-eyes White Dragon": "Battle Steer",
    "999.999": 230
  },
  {
    "1": 15,
    "Blue-eyes White Dragon": "Flame Swordsman",
    "999.999": 320
  },
  {
    "1": 16,
    "Blue-eyes White Dragon": "Time Wizard",
    "999.999": 999.999
  },
  {
    "1": 17,
    "Blue-eyes White Dragon": "Right Leg of the Forbidden One",
    "999.999": 999.999
  },
  {
    "1": 18,
    "Blue-eyes White Dragon": "Left Leg of the Forbidden One",
    "999.999": 999.999
  },
  {
    "1": 19,
    "Blue-eyes White Dragon": "Right Arm of the Forbidden One",
    "999.999": 999.999
  },
  {
    "1": 20,
    "Blue-eyes White Dragon": "Left Arm of the Forbidden One",
    "999.999": 999.999
  },
  {
    "1": 21,
    "Blue-eyes White Dragon": "Exodia the Forbidden",
    "999.999": 999.999
  },
  {
    "1": 22,
    "Blue-eyes White Dragon": "Summoned Skull",
    "999.999": 999.999
  },
  {
    "1": 23,
    "Blue-eyes White Dragon": "The Wicked Worm Beast",
    "999.999": 60
  },
  {
    "1": 24,
    "Blue-eyes White Dragon": "Skull Servant",
    "999.999": 10
  },
  {
    "1": 25,
    "Blue-eyes White Dragon": "Horn Imp",
    "999.999": 80
  },
  {
    "1": 26,
    "Blue-eyes White Dragon": "Battle Ox",
    "999.999": 999.999
  },
  {
    "1": 27,
    "Blue-eyes White Dragon": "Beaver Warrior",
    "999.999": 140
  },
  {
    "1": 28,
    "Blue-eyes White Dragon": "Rock Ogre Grotto #1",
    "999.999": 999.999
  },
  {
    "1": 29,
    "Blue-eyes White Dragon": "Mountain Warrior",
    "999.999": 35
  },
  {
    "1": 30,
    "Blue-eyes White Dragon": "Zombie Warrior",
    "999.999": 60
  },
  {
    "1": 31,
    "Blue-eyes White Dragon": "Koumori Dragon",
    "999.999": 140
  },
  {
    "1": 32,
    "Blue-eyes White Dragon": "Two-headed King Rex",
    "999.999": 160
  },
  {
    "1": 33,
    "Blue-eyes White Dragon": "Judge Man",
    "999.999": 1
  },
  {
    "1": 34,
    "Blue-eyes White Dragon": "Saggi the Dark Clown",
    "999.999": 60
  },
  {
    "1": 35,
    "Blue-eyes White Dragon": "Dark Magician",
    "999.999": 999.999
  },
  {
    "1": 36,
    "Blue-eyes White Dragon": "The Snake Hair",
    "999.999": 140
  },
  {
    "1": 37,
    "Blue-eyes White Dragon": "Gaia the Dragon Champion",
    "999.999": 999.999
  },
  {
    "1": 38,
    "Blue-eyes White Dragon": "Gaia the Fierce Knight",
    "999.999": 999.999
  },
  {
    "1": 39,
    "Blue-eyes White Dragon": "Curse of Dragon",
    "999.999": 999.999
  },
  {
    "1": 40,
    "Blue-eyes White Dragon": "Dragon Piper",
    "999.999": 55
  },
  {
    "1": 41,
    "Blue-eyes White Dragon": "Celtic Guardian",
    "999.999": 120
  },
  {
    "1": 42,
    "Blue-eyes White Dragon": "Illusionist Faceless Mage",
    "999.999": 320
  },
  {
    "1": 43,
    "Blue-eyes White Dragon": "Karbonala Warrior",
    "999.999": 140
  },
  {
    "1": 44,
    "Blue-eyes White Dragon": "Rogue Doll",
    "999.999": 120
  },
  {
    "1": 45,
    "Blue-eyes White Dragon": "Oscillo Hero #2",
    "999.999": 30
  },
  {
    "1": 46,
    "Blue-eyes White Dragon": "Griffore",
    "999.999": 140
  },
  {
    "1": 47,
    "Blue-eyes White Dragon": "Torike",
    "999.999": 45
  },
  {
    "1": 48,
    "Blue-eyes White Dragon": "Sangan",
    "999.999": 35
  },
  {
    "1": 49,
    "Blue-eyes White Dragon": "Big Insect",
    "999.999": 140
  },
  {
    "1": 50,
    "Blue-eyes White Dragon": "Basic Insect",
    "999.999": 25
  },
  {
    "1": 51,
    "Blue-eyes White Dragon": "Armored Lizard",
    "999.999": 999.999
  },
  {
    "1": 52,
    "Blue-eyes White Dragon": "Hercules Beetle",
    "999.999": 999.999
  },
  {
    "1": 53,
    "Blue-eyes White Dragon": "Killer Needle",
    "999.999": 70
  },
  {
    "1": 54,
    "Blue-eyes White Dragon": "Gokibore",
    "999.999": 999.999
  },
  {
    "1": 55,
    "Blue-eyes White Dragon": "Giant Flea",
    "999.999": 140
  },
  {
    "1": 56,
    "Blue-eyes White Dragon": "Larvae Moth",
    "999.999": 999.999
  },
  {
    "1": 57,
    "Blue-eyes White Dragon": "Great Moth",
    "999.999": 999.999
  },
  {
    "1": 58,
    "Blue-eyes White Dragon": "Kuriboh",
    "999.999": 10
  },
  {
    "1": 59,
    "Blue-eyes White Dragon": "Mammoth Graveyard",
    "999.999": 55
  },
  {
    "1": 60,
    "Blue-eyes White Dragon": "Great White",
    "999.999": 999.999
  },
  {
    "1": 61,
    "Blue-eyes White Dragon": "Wolf",
    "999.999": 55
  },
  {
    "1": 62,
    "Blue-eyes White Dragon": "Harpie Lady",
    "999.999": 999.999
  },
  {
    "1": 63,
    "Blue-eyes White Dragon": "Harpie Lady Sisters",
    "999.999": 999.999
  },
  {
    "1": 64,
    "Blue-eyes White Dragon": "Tiger Axe",
    "999.999": 999.999
  },
  {
    "1": 65,
    "Blue-eyes White Dragon": "Silver Fang",
    "999.999": 55
  },
  {
    "1": 66,
    "Blue-eyes White Dragon": "Kojikocy",
    "999.999": 140
  },
  {
    "1": 67,
    "Blue-eyes White Dragon": "Perfectly Ultimate Great Moth",
    "999.999": 999.999
  },
  {
    "1": 68,
    "Blue-eyes White Dragon": "Garoozis",
    "999.999": 290
  },
  {
    "1": 69,
    "Blue-eyes White Dragon": "Thousand Dragon",
    "999.999": 999.999
  },
  {
    "1": 70,
    "Blue-eyes White Dragon": "Fiend Kraken",
    "999.999": 120
  },
  {
    "1": 71,
    "Blue-eyes White Dragon": "Jellyfish",
    "999.999": 140
  },
  {
    "1": 72,
    "Blue-eyes White Dragon": "Cocoon of Evolution",
    "999.999": 999.999
  },
  {
    "1": 73,
    "Blue-eyes White Dragon": "Kairyu-Shin",
    "999.999": 290
  },
  {
    "1": 74,
    "Blue-eyes White Dragon": "Giant Soldier of Stone",
    "999.999": 290
  },
  {
    "1": 75,
    "Blue-eyes White Dragon": "Man-eating Plant",
    "999.999": 30
  },
  {
    "1": 76,
    "Blue-eyes White Dragon": "Krokodilus",
    "999.999": 80
  },
  {
    "1": 77,
    "Blue-eyes White Dragon": "Grappler",
    "999.999": 100
  },
  {
    "1": 78,
    "Blue-eyes White Dragon": "Axe Raider",
    "999.999": 160
  },
  {
    "1": 79,
    "Blue-eyes White Dragon": "Megazowler",
    "999.999": 500
  },
  {
    "1": 80,
    "Blue-eyes White Dragon": "Uraby",
    "999.999": 80
  },
  {
    "1": 81,
    "Blue-eyes White Dragon": "Crawling Dragon #2",
    "999.999": 160
  },
  {
    "1": 82,
    "Blue-eyes White Dragon": "Red-eyes B. Dragon",
    "999.999": 999.999
  },
  {
    "1": 83,
    "Blue-eyes White Dragon": "Castle of Dark Illusions",
    "999.999": 160
  },
  {
    "1": 84,
    "Blue-eyes White Dragon": "Reaper of the Cards",
    "999.999": 290
  },
  {
    "1": 85,
    "Blue-eyes White Dragon": "King of Yamimakai",
    "999.999": 350
  },
  {
    "1": 86,
    "Blue-eyes White Dragon": "Barox",
    "999.999": 180
  },
  {
    "1": 87,
    "Blue-eyes White Dragon": "Dark Chimera",
    "999.999": 200
  },
  {
    "1": 88,
    "Blue-eyes White Dragon": "Metal Guardian",
    "999.999": 290
  },
  {
    "1": 89,
    "Blue-eyes White Dragon": "Catapult Turtle",
    "999.999": 200
  },
  {
    "1": 90,
    "Blue-eyes White Dragon": "Gyakutenno Megami",
    "999.999": 500
  },
  {
    "1": 91,
    "Blue-eyes White Dragon": "Mystic Horseman",
    "999.999": 999.999
  },
  {
    "1": 92,
    "Blue-eyes White Dragon": "Rabid Horseman",
    "999.999": 999.999
  },
  {
    "1": 93,
    "Blue-eyes White Dragon": "Zanki",
    "999.999": 260
  },
  {
    "1": 94,
    "Blue-eyes White Dragon": "Crawling Dragon",
    "999.999": 200
  },
  {
    "1": 95,
    "Blue-eyes White Dragon": "Crass Clown",
    "999.999": 140
  },
  {
    "1": 96,
    "Blue-eyes White Dragon": "Armored Zombie",
    "999.999": 260
  },
  {
    "1": 97,
    "Blue-eyes White Dragon": "Dragon Zombie",
    "999.999": 200
  },
  {
    "1": 98,
    "Blue-eyes White Dragon": "Clown Zombie",
    "999.999": 140
  },
  {
    "1": 99,
    "Blue-eyes White Dragon": "Pumpking the King of Ghosts",
    "999.999": 500
  },
  {
    "1": 100,
    "Blue-eyes White Dragon": "Battle Warrior",
    "999.999": 40
  },
  {
    "1": 101,
    "Blue-eyes White Dragon": "Wings of Wicked Flame",
    "999.999": 30
  },
  {
    "1": 102,
    "Blue-eyes White Dragon": "Mask of Darkness",
    "999.999": 30
  },
  {
    "1": 103,
    "Blue-eyes White Dragon": "Job-Change Mirror",
    "999.999": 999.999
  },
  {
    "1": 104,
    "Blue-eyes White Dragon": "Curtain of the Dark Ones",
    "999.999": 25
  },
  {
    "1": 105,
    "Blue-eyes White Dragon": "Tomozaurus",
    "999.999": 20
  },
  {
    "1": 106,
    "Blue-eyes White Dragon": "Spirit of the Winds",
    "999.999": 230
  },
  {
    "1": 107,
    "Blue-eyes White Dragon": "Kageningen",
    "999.999": 30
  },
  {
    "1": 108,
    "Blue-eyes White Dragon": "Graveyard and the Hand of Invitation",
    "999.999": 35
  },
  {
    "1": 109,
    "Blue-eyes White Dragon": "Goddess with the Third Eye",
    "999.999": 70
  },
  {
    "1": 110,
    "Blue-eyes White Dragon": "Hero of the East",
    "999.999": 60
  },
  {
    "1": 111,
    "Blue-eyes White Dragon": "Doma The Angel of Silence",
    "999.999": 200
  },
  {
    "1": 112,
    "Blue-eyes White Dragon": "That Which Feeds on Life",
    "999.999": 70
  },
  {
    "1": 113,
    "Blue-eyes White Dragon": "Dark Gray",
    "999.999": 40
  },
  {
    "1": 114,
    "Blue-eyes White Dragon": "White Magical Hat",
    "999.999": 40
  },
  {
    "1": 115,
    "Blue-eyes White Dragon": "Kamion Wizard",
    "999.999": 120
  },
  {
    "1": 116,
    "Blue-eyes White Dragon": "Nightmare Scorpion",
    "999.999": 40
  },
  {
    "1": 117,
    "Blue-eyes White Dragon": "Spirit of the Books",
    "999.999": 120
  },
  {
    "1": 118,
    "Blue-eyes White Dragon": "Supporter in the Shadows",
    "999.999": 55
  },
  {
    "1": 119,
    "Blue-eyes White Dragon": "Trial of Nightmares",
    "999.999": 70
  },
  {
    "1": 120,
    "Blue-eyes White Dragon": "Dream Clown",
    "999.999": 60
  },
  {
    "1": 121,
    "Blue-eyes White Dragon": "Sleeping Lion",
    "999.999": 120
  },
  {
    "1": 122,
    "Blue-eyes White Dragon": "Yamatano Dragon Scroll",
    "999.999": 25
  },
  {
    "1": 123,
    "Blue-eyes White Dragon": "Dark Plant",
    "999.999": 15
  },
  {
    "1": 124,
    "Blue-eyes White Dragon": "Ancient Tool",
    "999.999": 230
  },
  {
    "1": 125,
    "Blue-eyes White Dragon": "Faith Bird",
    "999.999": 120
  },
  {
    "1": 126,
    "Blue-eyes White Dragon": "Orion the Battle King",
    "999.999": 290
  },
  {
    "1": 127,
    "Blue-eyes White Dragon": "Ansatsu",
    "999.999": 180
  },
  {
    "1": 128,
    "Blue-eyes White Dragon": "LaMoon",
    "999.999": 180
  },
  {
    "1": 129,
    "Blue-eyes White Dragon": "Nemuriko",
    "999.999": 30
  },
  {
    "1": 130,
    "Blue-eyes White Dragon": "Weather Control",
    "999.999": 20
  },
  {
    "1": 131,
    "Blue-eyes White Dragon": "Octoberser",
    "999.999": 200
  },
  {
    "1": 132,
    "Blue-eyes White Dragon": "The 13th Grave",
    "999.999": 60
  },
  {
    "1": 133,
    "Blue-eyes White Dragon": "Charubin the Fire Knight",
    "999.999": 50
  },
  {
    "1": 134,
    "Blue-eyes White Dragon": "Mystical Capture Chain",
    "999.999": 30
  },
  {
    "1": 135,
    "Blue-eyes White Dragon": "Fiend's Hand",
    "999.999": 25
  },
  {
    "1": 136,
    "Blue-eyes White Dragon": "Witty Phantom",
    "999.999": 140
  },
  {
    "1": 137,
    "Blue-eyes White Dragon": "Mystery Hand",
    "999.999": 20
  },
  {
    "1": 138,
    "Blue-eyes White Dragon": "Dragon Statue",
    "999.999": 55
  },
  {
    "1": 139,
    "Blue-eyes White Dragon": "Blue-eyed Silver Zombie",
    "999.999": 35
  },
  {
    "1": 140,
    "Blue-eyes White Dragon": "Toad Master",
    "999.999": 55
  },
  {
    "1": 141,
    "Blue-eyes White Dragon": "Spiked Snail",
    "999.999": 55
  },
  {
    "1": 142,
    "Blue-eyes White Dragon": "Flame Manipulator",
    "999.999": 50
  },
  {
    "1": 143,
    "Blue-eyes White Dragon": "Necrolancer the Timelord",
    "999.999": 40
  },
  {
    "1": 144,
    "Blue-eyes White Dragon": "Djinn the Watcher of the Wind",
    "999.999": 35
  },
  {
    "1": 145,
    "Blue-eyes White Dragon": "The Bewitching Phantom Thief",
    "999.999": 30
  },
  {
    "1": 146,
    "Blue-eyes White Dragon": "Temple of Skulls",
    "999.999": 70
  },
  {
    "1": 147,
    "Blue-eyes White Dragon": "Monster Egg",
    "999.999": 999.999
  },
  {
    "1": 148,
    "Blue-eyes White Dragon": "The Shadow Who Controls the Dark",
    "999.999": 30
  },
  {
    "1": 149,
    "Blue-eyes White Dragon": "Lord of the Lamp",
    "999.999": 120
  },
  {
    "1": 150,
    "Blue-eyes White Dragon": "Akihiron",
    "999.999": 230
  },
  {
    "1": 151,
    "Blue-eyes White Dragon": "Rhaimundos of the Red Sword",
    "999.999": 100
  },
  {
    "1": 152,
    "Blue-eyes White Dragon": "The Melting Red Shadow",
    "999.999": 25
  },
  {
    "1": 153,
    "Blue-eyes White Dragon": "Dokuroizo the Grim Reaper",
    "999.999": 60
  },
  {
    "1": 154,
    "Blue-eyes White Dragon": "Fire Reaper",
    "999.999": 25
  },
  {
    "1": 155,
    "Blue-eyes White Dragon": "Larvas",
    "999.999": 45
  },
  {
    "1": 156,
    "Blue-eyes White Dragon": "Hard Armor",
    "999.999": 30
  },
  {
    "1": 157,
    "Blue-eyes White Dragon": "Firegrass",
    "999.999": 30
  },
  {
    "1": 158,
    "Blue-eyes White Dragon": "Man Eater",
    "999.999": 30
  },
  {
    "1": 159,
    "Blue-eyes White Dragon": "Dig Beak",
    "999.999": 30
  },
  {
    "1": 160,
    "Blue-eyes White Dragon": "M-warrior #1",
    "999.999": 30
  },
  {
    "1": 161,
    "Blue-eyes White Dragon": "M-warrior #2",
    "999.999": 30
  },
  {
    "1": 162,
    "Blue-eyes White Dragon": "Tainted Wisdom",
    "999.999": 55
  },
  {
    "1": 163,
    "Blue-eyes White Dragon": "Lisark",
    "999.999": 120
  },
  {
    "1": 164,
    "Blue-eyes White Dragon": "Lord of Zemia",
    "999.999": 80
  },
  {
    "1": 165,
    "Blue-eyes White Dragon": "The Judgement Hand",
    "999.999": 60
  },
  {
    "1": 166,
    "Blue-eyes White Dragon": "Mysterious Puppeteer",
    "999.999": 100
  },
  {
    "1": 167,
    "Blue-eyes White Dragon": "Ancient Jar",
    "999.999": 15
  },
  {
    "1": 168,
    "Blue-eyes White Dragon": "Darkfire Dragon",
    "999.999": 140
  },
  {
    "1": 169,
    "Blue-eyes White Dragon": "Dark King of the Abyss",
    "999.999": 55
  },
  {
    "1": 170,
    "Blue-eyes White Dragon": "Spirit of the Harp",
    "999.999": 160
  },
  {
    "1": 171,
    "Blue-eyes White Dragon": "Big Eye",
    "999.999": 70
  },
  {
    "1": 172,
    "Blue-eyes White Dragon": "Armaill",
    "999.999": 55
  },
  {
    "1": 173,
    "Blue-eyes White Dragon": "Dark Prisoner",
    "999.999": 35
  },
  {
    "1": 174,
    "Blue-eyes White Dragon": "Hurricail",
    "999.999": 25
  },
  {
    "1": 175,
    "Blue-eyes White Dragon": "Ancient Brain",
    "999.999": 40
  },
  {
    "1": 176,
    "Blue-eyes White Dragon": "Fire Eye",
    "999.999": 30
  },
  {
    "1": 177,
    "Blue-eyes White Dragon": "Monsturtle",
    "999.999": 45
  },
  {
    "1": 178,
    "Blue-eyes White Dragon": "Claw Reacher",
    "999.999": 45
  },
  {
    "1": 179,
    "Blue-eyes White Dragon": "Phantom Dewan",
    "999.999": 30
  },
  {
    "1": 180,
    "Blue-eyes White Dragon": "Arlownay",
    "999.999": 45
  },
  {
    "1": 181,
    "Blue-eyes White Dragon": "Dark Shade",
    "999.999": 55
  },
  {
    "1": 182,
    "Blue-eyes White Dragon": "Masked Clown",
    "999.999": 25
  },
  {
    "1": 183,
    "Blue-eyes White Dragon": "Lucky Trinket",
    "999.999": 30
  },
  {
    "1": 184,
    "Blue-eyes White Dragon": "Genin",
    "999.999": 30
  },
  {
    "1": 185,
    "Blue-eyes White Dragon": "Eyearmor",
    "999.999": 25
  },
  {
    "1": 186,
    "Blue-eyes White Dragon": "Fiend Refrection #2",
    "999.999": 100
  },
  {
    "1": 187,
    "Blue-eyes White Dragon": "Gate Deeg",
    "999.999": 30
  },
  {
    "1": 188,
    "Blue-eyes White Dragon": "Synchar",
    "999.999": 40
  },
  {
    "1": 189,
    "Blue-eyes White Dragon": "Fusionist",
    "999.999": 35
  },
  {
    "1": 190,
    "Blue-eyes White Dragon": "Akakieisu",
    "999.999": 45
  },
  {
    "1": 191,
    "Blue-eyes White Dragon": "LALA Li-oon",
    "999.999": 25
  },
  {
    "1": 192,
    "Blue-eyes White Dragon": "Key Mace",
    "999.999": 15
  },
  {
    "1": 193,
    "Blue-eyes White Dragon": "Turtle Tiger",
    "999.999": 100
  },
  {
    "1": 194,
    "Blue-eyes White Dragon": "Terra the Terrible",
    "999.999": 100
  },
  {
    "1": 195,
    "Blue-eyes White Dragon": "Doron",
    "999.999": 30
  },
  {
    "1": 196,
    "Blue-eyes White Dragon": "Arma Knight",
    "999.999": 70
  },
  {
    "1": 197,
    "Blue-eyes White Dragon": "Mech Mole Zombie",
    "999.999": 20
  },
  {
    "1": 198,
    "Blue-eyes White Dragon": "Happy Lover",
    "999.999": 30
  },
  {
    "1": 199,
    "Blue-eyes White Dragon": "Penguin Knight",
    "999.999": 40
  },
  {
    "1": 200,
    "Blue-eyes White Dragon": "Petit Dragon",
    "999.999": 30
  },
  {
    "1": 201,
    "Blue-eyes White Dragon": "Frenzied Panda",
    "999.999": 70
  },
  {
    "1": 202,
    "Blue-eyes White Dragon": "Air Marmot of Nefariousness",
    "999.999": 20
  },
  {
    "1": 203,
    "Blue-eyes White Dragon": "Phantom Ghost",
    "999.999": 30
  },
  {
    "1": 204,
    "Blue-eyes White Dragon": "Mabarrel",
    "999.999": 230
  },
  {
    "1": 205,
    "Blue-eyes White Dragon": "Dorover",
    "999.999": 40
  },
  {
    "1": 206,
    "Blue-eyes White Dragon": "Twin Long Rods #1",
    "999.999": 35
  },
  {
    "1": 207,
    "Blue-eyes White Dragon": "Droll Bird",
    "999.999": 25
  },
  {
    "1": 208,
    "Blue-eyes White Dragon": "Petit Angel",
    "999.999": 30
  },
  {
    "1": 209,
    "Blue-eyes White Dragon": "Winged Cleaver",
    "999.999": 30
  },
  {
    "1": 210,
    "Blue-eyes White Dragon": "Hinotama Soul",
    "999.999": 25
  },
  {
    "1": 211,
    "Blue-eyes White Dragon": "Kaminarikozou",
    "999.999": 30
  },
  {
    "1": 212,
    "Blue-eyes White Dragon": "Meotoko",
    "999.999": 30
  },
  {
    "1": 213,
    "Blue-eyes White Dragon": "Aqua Madoor",
    "999.999": 260
  },
  {
    "1": 214,
    "Blue-eyes White Dragon": "Kagemusha of the Blue Flame",
    "999.999": 25
  },
  {
    "1": 215,
    "Blue-eyes White Dragon": "Flame Ghost",
    "999.999": 45
  },
  {
    "1": 216,
    "Blue-eyes White Dragon": "Dryad",
    "999.999": 120
  },
  {
    "1": 217,
    "Blue-eyes White Dragon": "B. Skull Dragon",
    "999.999": 999.999
  },
  {
    "1": 218,
    "Blue-eyes White Dragon": "Two-mouth Darkruler",
    "999.999": 35
  },
  {
    "1": 219,
    "Blue-eyes White Dragon": "Solitude",
    "999.999": 55
  },
  {
    "1": 220,
    "Blue-eyes White Dragon": "Masked Sorcerer",
    "999.999": 80
  },
  {
    "1": 221,
    "Blue-eyes White Dragon": "Kumootoko",
    "999.999": 60
  },
  {
    "1": 222,
    "Blue-eyes White Dragon": "Midnight Fiend",
    "999.999": 30
  },
  {
    "1": 223,
    "Blue-eyes White Dragon": "Roaring Ocean Snake",
    "999.999": 550
  },
  {
    "1": 224,
    "Blue-eyes White Dragon": "Trap Master",
    "999.999": 35
  },
  {
    "1": 225,
    "Blue-eyes White Dragon": "Fiend Sword",
    "999.999": 70
  },
  {
    "1": 226,
    "Blue-eyes White Dragon": "Skull Stalker",
    "999.999": 40
  },
  {
    "1": 227,
    "Blue-eyes White Dragon": "Hitodenchak",
    "999.999": 30
  },
  {
    "1": 228,
    "Blue-eyes White Dragon": "Wood Remains",
    "999.999": 50
  },
  {
    "1": 229,
    "Blue-eyes White Dragon": "Hourglass of Life",
    "999.999": 30
  },
  {
    "1": 230,
    "Blue-eyes White Dragon": "Rare Fish",
    "999.999": 140
  },
  {
    "1": 231,
    "Blue-eyes White Dragon": "Wood Clown",
    "999.999": 55
  },
  {
    "1": 232,
    "Blue-eyes White Dragon": "Madjinn Gunn",
    "999.999": 30
  },
  {
    "1": 233,
    "Blue-eyes White Dragon": "Dark Titan of Terror",
    "999.999": 120
  },
  {
    "1": 234,
    "Blue-eyes White Dragon": "Beautiful Headhuntress",
    "999.999": 120
  },
  {
    "1": 235,
    "Blue-eyes White Dragon": "Wodan the Resident of the Forest",
    "999.999": 999.999
  },
  {
    "1": 236,
    "Blue-eyes White Dragon": "Guardian of the Labyrinth",
    "999.999": 70
  },
  {
    "1": 237,
    "Blue-eyes White Dragon": "Haniwa",
    "999.999": 20
  },
  {
    "1": 238,
    "Blue-eyes White Dragon": "Yashinoki",
    "999.999": 30
  },
  {
    "1": 239,
    "Blue-eyes White Dragon": "Vishwar Randi",
    "999.999": 35
  },
  {
    "1": 240,
    "Blue-eyes White Dragon": "The Drdek",
    "999.999": 30
  },
  {
    "1": 241,
    "Blue-eyes White Dragon": "Dark Assailant",
    "999.999": 120
  },
  {
    "1": 242,
    "Blue-eyes White Dragon": "Candle of Fate",
    "999.999": 25
  },
  {
    "1": 243,
    "Blue-eyes White Dragon": "Water Element",
    "999.999": 35
  },
  {
    "1": 244,
    "Blue-eyes White Dragon": "Dissolverock",
    "999.999": 50
  },
  {
    "1": 245,
    "Blue-eyes White Dragon": "Meda Bat",
    "999.999": 25
  },
  {
    "1": 246,
    "Blue-eyes White Dragon": "One Who Hunts Souls",
    "999.999": 60
  },
  {
    "1": 247,
    "Blue-eyes White Dragon": "Root Water",
    "999.999": 40
  },
  {
    "1": 248,
    "Blue-eyes White Dragon": "Master & Expert",
    "999.999": 70
  },
  {
    "1": 249,
    "Blue-eyes White Dragon": "Water Omotics",
    "999.999": 120
  },
  {
    "1": 250,
    "Blue-eyes White Dragon": "Hyo",
    "999.999": 55
  },
  {
    "1": 251,
    "Blue-eyes White Dragon": "Enchanting Mermaid",
    "999.999": 60
  },
  {
    "1": 252,
    "Blue-eyes White Dragon": "Nekogal #1",
    "999.999": 999.999
  },
  {
    "1": 253,
    "Blue-eyes White Dragon": "Angelwitch",
    "999.999": 45
  },
  {
    "1": 254,
    "Blue-eyes White Dragon": "Embryonic Beast",
    "999.999": 25
  },
  {
    "1": 255,
    "Blue-eyes White Dragon": "Prevent Rat",
    "999.999": 100
  },
  {
    "1": 256,
    "Blue-eyes White Dragon": "Dimensional Warrior",
    "999.999": 70
  },
  {
    "1": 257,
    "Blue-eyes White Dragon": "Stone Armadiller",
    "999.999": 55
  },
  {
    "1": 258,
    "Blue-eyes White Dragon": "Beastking of the Swamps",
    "999.999": 60
  },
  {
    "1": 259,
    "Blue-eyes White Dragon": "Ancient Sorcerer",
    "999.999": 80
  },
  {
    "1": 260,
    "Blue-eyes White Dragon": "Lunar Queen Elzaim",
    "999.999": 45
  },
  {
    "1": 261,
    "Blue-eyes White Dragon": "Wicked Mirror",
    "999.999": 30
  },
  {
    "1": 262,
    "Blue-eyes White Dragon": "The Little Swordsman of Aile",
    "999.999": 60
  },
  {
    "1": 263,
    "Blue-eyes White Dragon": "Rock Ogre Grotto #2",
    "999.999": 60
  },
  {
    "1": 264,
    "Blue-eyes White Dragon": "Wing Egg Elf",
    "999.999": 45
  },
  {
    "1": 265,
    "Blue-eyes White Dragon": "The Furious Sea King",
    "999.999": 30
  },
  {
    "1": 266,
    "Blue-eyes White Dragon": "Princess of Tsurugi",
    "999.999": 35
  },
  {
    "1": 267,
    "Blue-eyes White Dragon": "Unknown Warrior of Fiend",
    "999.999": 30
  },
  {
    "1": 268,
    "Blue-eyes White Dragon": "Sectarian of Secrets",
    "999.999": 25
  },
  {
    "1": 269,
    "Blue-eyes White Dragon": "Versago the Destroyer",
    "999.999": 55
  },
  {
    "1": 270,
    "Blue-eyes White Dragon": "Wetha",
    "999.999": 50
  },
  {
    "1": 271,
    "Blue-eyes White Dragon": "Megirus Light",
    "999.999": 30
  },
  {
    "1": 272,
    "Blue-eyes White Dragon": "Mavelus",
    "999.999": 70
  },
  {
    "1": 273,
    "Blue-eyes White Dragon": "Ancient Tree of Enlightenment",
    "999.999": 60
  },
  {
    "1": 274,
    "Blue-eyes White Dragon": "Green Phantom King",
    "999.999": 60
  },
  {
    "1": 275,
    "Blue-eyes White Dragon": "Ground Attacker Bugroth",
    "999.999": 100
  },
  {
    "1": 276,
    "Blue-eyes White Dragon": "Ray & Temperature",
    "999.999": 55
  },
  {
    "1": 277,
    "Blue-eyes White Dragon": "Gorgon Egg",
    "999.999": 35
  },
  {
    "1": 278,
    "Blue-eyes White Dragon": "Petit Moth",
    "999.999": 10
  },
  {
    "1": 279,
    "Blue-eyes White Dragon": "King Fog",
    "999.999": 50
  },
  {
    "1": 280,
    "Blue-eyes White Dragon": "Protector of the Throne",
    "999.999": 80
  },
  {
    "1": 281,
    "Blue-eyes White Dragon": "Mystic Clown",
    "999.999": 100
  },
  {
    "1": 282,
    "Blue-eyes White Dragon": "Mystical Sheep #2",
    "999.999": 45
  },
  {
    "1": 283,
    "Blue-eyes White Dragon": "Holograh",
    "999.999": 45
  },
  {
    "1": 284,
    "Blue-eyes White Dragon": "Tao the Chanter",
    "999.999": 999.999
  },
  {
    "1": 285,
    "Blue-eyes White Dragon": "Serpent Marauder",
    "999.999": 30
  },
  {
    "1": 286,
    "Blue-eyes White Dragon": "Gatekeeper",
    "999.999": 290
  },
  {
    "1": 287,
    "Blue-eyes White Dragon": "Ogre of the Black Shadow",
    "999.999": 120
  },
  {
    "1": 288,
    "Blue-eyes White Dragon": "Dark Artist",
    "999.999": 999.999
  },
  {
    "1": 289,
    "Blue-eyes White Dragon": "Change Slime",
    "999.999": 15
  },
  {
    "1": 290,
    "Blue-eyes White Dragon": "Moon Envoy",
    "999.999": 60
  },
  {
    "1": 291,
    "Blue-eyes White Dragon": "Fireyarou",
    "999.999": 80
  },
  {
    "1": 292,
    "Blue-eyes White Dragon": "Psychic Kappa",
    "999.999": 30
  },
  {
    "1": 293,
    "Blue-eyes White Dragon": "Masaki the Legendary Swordsman",
    "999.999": 70
  },
  {
    "1": 294,
    "Blue-eyes White Dragon": "Dragoness the Wicked Knight",
    "999.999": 60
  },
  {
    "1": 295,
    "Blue-eyes White Dragon": "Bio Plant",
    "999.999": 50
  },
  {
    "1": 296,
    "Blue-eyes White Dragon": "One-eyed Shield Dragon",
    "999.999": 55
  },
  {
    "1": 297,
    "Blue-eyes White Dragon": "Cyber Soldier of Darkworld",
    "999.999": 120
  },
  {
    "1": 298,
    "Blue-eyes White Dragon": "Wicked Dragon with the Ersatz Head",
    "999.999": 45
  },
  {
    "1": 299,
    "Blue-eyes White Dragon": "Sonic Maid",
    "999.999": 999.999
  },
  {
    "1": 300,
    "Blue-eyes White Dragon": "Kurama",
    "999.999": 35
  },
  {
    "1": 301,
    "Blue-eyes White Dragon": "Legendary Sword",
    "999.999": 800
  },
  {
    "1": 302,
    "Blue-eyes White Dragon": "Sword of Dark Destruction",
    "999.999": 800
  },
  {
    "1": 303,
    "Blue-eyes White Dragon": "Dark Energy",
    "999.999": 800
  },
  {
    "1": 304,
    "Blue-eyes White Dragon": "Axe of Despair",
    "999.999": 800
  },
  {
    "1": 305,
    "Blue-eyes White Dragon": "Laser Cannon Armor",
    "999.999": 800
  },
  {
    "1": 306,
    "Blue-eyes White Dragon": "Insect Armor with Laser Cannon",
    "999.999": 800
  },
  {
    "1": 307,
    "Blue-eyes White Dragon": "Elf's Light",
    "999.999": 800
  },
  {
    "1": 308,
    "Blue-eyes White Dragon": "Beast Fangs",
    "999.999": 800
  },
  {
    "1": 309,
    "Blue-eyes White Dragon": "Steel Shell",
    "999.999": 800
  },
  {
    "1": 310,
    "Blue-eyes White Dragon": "Vile Germs",
    "999.999": 800
  },
  {
    "1": 311,
    "Blue-eyes White Dragon": "Black Pendant",
    "999.999": 800
  },
  {
    "1": 312,
    "Blue-eyes White Dragon": "Silver Bow and Arrow",
    "999.999": 800
  },
  {
    "1": 313,
    "Blue-eyes White Dragon": "Horn of Light",
    "999.999": 800
  },
  {
    "1": 314,
    "Blue-eyes White Dragon": "Horn of the Unicorn",
    "999.999": 800
  },
  {
    "1": 315,
    "Blue-eyes White Dragon": "Dragon Treasure",
    "999.999": 800
  },
  {
    "1": 316,
    "Blue-eyes White Dragon": "Electro-whip",
    "999.999": 800
  },
  {
    "1": 317,
    "Blue-eyes White Dragon": "Cyber Shield",
    "999.999": 800
  },
  {
    "1": 318,
    "Blue-eyes White Dragon": "Elegant Egotist",
    "999.999": 999.999
  },
  {
    "1": 319,
    "Blue-eyes White Dragon": "Mystical Moon",
    "999.999": 800
  },
  {
    "1": 320,
    "Blue-eyes White Dragon": "Stop Defense",
    "999.999": 800
  },
  {
    "1": 321,
    "Blue-eyes White Dragon": "Malevolent Nuzzler",
    "999.999": 800
  },
  {
    "1": 322,
    "Blue-eyes White Dragon": "Violet Crystal",
    "999.999": 800
  },
  {
    "1": 323,
    "Blue-eyes White Dragon": "Book of Secret Arts",
    "999.999": 800
  },
  {
    "1": 324,
    "Blue-eyes White Dragon": "Invigoration",
    "999.999": 800
  },
  {
    "1": 325,
    "Blue-eyes White Dragon": "Machine Conversion Factory",
    "999.999": 999.999
  },
  {
    "1": 326,
    "Blue-eyes White Dragon": "Raise Body Heat",
    "999.999": 800
  },
  {
    "1": 327,
    "Blue-eyes White Dragon": "Follow Wind",
    "999.999": 800
  },
  {
    "1": 328,
    "Blue-eyes White Dragon": "Power of Kaishin",
    "999.999": 800
  },
  {
    "1": 329,
    "Blue-eyes White Dragon": "Dragon Capture Jar",
    "999.999": 999.999
  },
  {
    "1": 330,
    "Blue-eyes White Dragon": "Forest",
    "999.999": 55
  },
  {
    "1": 331,
    "Blue-eyes White Dragon": "Wasteland",
    "999.999": 55
  },
  {
    "1": 332,
    "Blue-eyes White Dragon": "Mountain",
    "999.999": 55
  },
  {
    "1": 333,
    "Blue-eyes White Dragon": "Sogen",
    "999.999": 55
  },
  {
    "1": 334,
    "Blue-eyes White Dragon": "Umi",
    "999.999": 55
  },
  {
    "1": 335,
    "Blue-eyes White Dragon": "Yami",
    "999.999": 55
  },
  {
    "1": 336,
    "Blue-eyes White Dragon": "Dark Hole",
    "999.999": 20
  },
  {
    "1": 337,
    "Blue-eyes White Dragon": "Raigeki",
    "999.999": 999.999
  },
  {
    "1": 338,
    "Blue-eyes White Dragon": "Mooyan Curry",
    "999.999": 999.999
  },
  {
    "1": 339,
    "Blue-eyes White Dragon": "Red Medicine",
    "999.999": 55
  },
  {
    "1": 340,
    "Blue-eyes White Dragon": "Goblin's Secret Remedy",
    "999.999": 20
  },
  {
    "1": 341,
    "Blue-eyes White Dragon": "Soul of the Pure",
    "999.999": 35
  },
  {
    "1": 342,
    "Blue-eyes White Dragon": "Dian Keto the Cure Master",
    "999.999": 999.999
  },
  {
    "1": 343,
    "Blue-eyes White Dragon": "Sparks",
    "999.999": 10
  },
  {
    "1": 344,
    "Blue-eyes White Dragon": "Hinotama",
    "999.999": 55
  },
  {
    "1": 345,
    "Blue-eyes White Dragon": "Final Flame",
    "999.999": 20
  },
  {
    "1": 346,
    "Blue-eyes White Dragon": "Ookazi",
    "999.999": 35
  },
  {
    "1": 347,
    "Blue-eyes White Dragon": "Tremendous Fire",
    "999.999": 999.999
  },
  {
    "1": 348,
    "Blue-eyes White Dragon": "Swords of Revealing Light",
    "999.999": 999.999
  },
  {
    "1": 349,
    "Blue-eyes White Dragon": "Spellbinding Circle",
    "999.999": 999.999
  },
  {
    "1": 350,
    "Blue-eyes White Dragon": "Dark-piercing Light",
    "999.999": 999.999
  },
  {
    "1": 351,
    "Blue-eyes White Dragon": "Yaranzo",
    "999.999": 160
  },
  {
    "1": 352,
    "Blue-eyes White Dragon": "Kanan the Swordmistress",
    "999.999": 160
  },
  {
    "1": 353,
    "Blue-eyes White Dragon": "Takriminos",
    "999.999": 140
  },
  {
    "1": 354,
    "Blue-eyes White Dragon": "Stuffed Animal",
    "999.999": 60
  },
  {
    "1": 355,
    "Blue-eyes White Dragon": "Megasonic Eye",
    "999.999": 290
  },
  {
    "1": 356,
    "Blue-eyes White Dragon": "Super War-lion",
    "999.999": ""
  },
  {
    "1": 357,
    "Blue-eyes White Dragon": "Yamadron",
    "999.999": 320
  },
  {
    "1": 358,
    "Blue-eyes White Dragon": "Seiyaryu",
    "999.999": 1.7
  },
  {
    "1": 359,
    "Blue-eyes White Dragon": "Three-legged Zombies",
    "999.999": 50
  },
  {
    "1": 360,
    "Blue-eyes White Dragon": "Zera The Mant",
    "999.999": ""
  },
  {
    "1": 361,
    "Blue-eyes White Dragon": "Flying Penguin",
    "999.999": 70
  },
  {
    "1": 362,
    "Blue-eyes White Dragon": "Millennium Shield",
    "999.999": 200
  },
  {
    "1": 363,
    "Blue-eyes White Dragon": "Fairy's Gift",
    "999.999": 120
  },
  {
    "1": 364,
    "Blue-eyes White Dragon": "Black Luster Soldier",
    "999.999": ""
  },
  {
    "1": 365,
    "Blue-eyes White Dragon": "Fiend's Mirror",
    "999.999": ""
  },
  {
    "1": 366,
    "Blue-eyes White Dragon": "Labyrinth Wall",
    "999.999": 200
  },
  {
    "1": 367,
    "Blue-eyes White Dragon": "Jirai Gumo",
    "999.999": 80
  },
  {
    "1": 368,
    "Blue-eyes White Dragon": "Shadow Ghoul",
    "999.999": 180
  },
  {
    "1": 369,
    "Blue-eyes White Dragon": "Wall Shadow",
    "999.999": 999.999
  },
  {
    "1": 370,
    "Blue-eyes White Dragon": "Labyrinth Tank",
    "999.999": 999.999
  },
  {
    "1": 371,
    "Blue-eyes White Dragon": "Sanga of the Thunder",
    "999.999": 999.999
  },
  {
    "1": 372,
    "Blue-eyes White Dragon": "Kazejin",
    "999.999": 999.999
  },
  {
    "1": 373,
    "Blue-eyes White Dragon": "Suijin",
    "999.999": 999.999
  },
  {
    "1": 374,
    "Blue-eyes White Dragon": "Gate Guardian",
    "999.999": ""
  },
  {
    "1": 375,
    "Blue-eyes White Dragon": "Dungeon Worm",
    "999.999": 290
  },
  {
    "1": 376,
    "Blue-eyes White Dragon": "Monster Tamer",
    "999.999": 320
  },
  {
    "1": 377,
    "Blue-eyes White Dragon": "Ryu-kishin Powered",
    "999.999": 160
  },
  {
    "1": 378,
    "Blue-eyes White Dragon": "Swordstalker",
    "999.999": 400
  },
  {
    "1": 379,
    "Blue-eyes White Dragon": "La Jinn the Mystical Genie",
    "999.999": 160
  },
  {
    "1": 380,
    "Blue-eyes White Dragon": "Blue-eyes Ultimate Dragon",
    "999.999": ""
  },
  {
    "1": 381,
    "Blue-eyes White Dragon": "Toon Alligator",
    "999.999": 120
  },
  {
    "1": 382,
    "Blue-eyes White Dragon": "Rude Kaiser",
    "999.999": 320
  },
  {
    "1": 383,
    "Blue-eyes White Dragon": "Parrot Dragon",
    "999.999": 290
  },
  {
    "1": 384,
    "Blue-eyes White Dragon": "Dark Rabbit",
    "999.999": 120
  },
  {
    "1": 385,
    "Blue-eyes White Dragon": "Bickuribox",
    "999.999": 900
  },
  {
    "1": 386,
    "Blue-eyes White Dragon": "Harpie's Pet Dragon",
    "999.999": 999.999
  },
  {
    "1": 387,
    "Blue-eyes White Dragon": "Mystic Lamp",
    "999.999": 15
  },
  {
    "1": 388,
    "Blue-eyes White Dragon": "Pendulum Machine",
    "999.999": 1
  },
  {
    "1": 389,
    "Blue-eyes White Dragon": "Giltia the D. Knight",
    "999.999": 290
  },
  {
    "1": 390,
    "Blue-eyes White Dragon": "Launcher Spider",
    "999.999": 999.999
  },
  {
    "1": 391,
    "Blue-eyes White Dragon": "Zoa",
    "999.999": 999.999
  },
  {
    "1": 392,
    "Blue-eyes White Dragon": "Metalzoa",
    "999.999": 999.999
  },
  {
    "1": 393,
    "Blue-eyes White Dragon": "Zone Eater",
    "999.999": 10
  },
  {
    "1": 394,
    "Blue-eyes White Dragon": "Steel Scorpion",
    "999.999": 10
  },
  {
    "1": 395,
    "Blue-eyes White Dragon": "Dancing Elf",
    "999.999": 10
  },
  {
    "1": 396,
    "Blue-eyes White Dragon": "Ocubeam",
    "999.999": 260
  },
  {
    "1": 397,
    "Blue-eyes White Dragon": "Leghul",
    "999.999": 15
  },
  {
    "1": 398,
    "Blue-eyes White Dragon": "Ooguchi",
    "999.999": 10
  },
  {
    "1": 399,
    "Blue-eyes White Dragon": "Swordsman from a Foreign Land",
    "999.999": 10
  },
  {
    "1": 400,
    "Blue-eyes White Dragon": "Emperor of the Land and Sea",
    "999.999": 290
  },
  {
    "1": 401,
    "Blue-eyes White Dragon": "Ushi Oni",
    "999.999": 700
  },
  {
    "1": 402,
    "Blue-eyes White Dragon": "Monster Eye",
    "999.999": 15
  },
  {
    "1": 403,
    "Blue-eyes White Dragon": "Leogun",
    "999.999": 290
  },
  {
    "1": 404,
    "Blue-eyes White Dragon": "Tatsunootoshigo",
    "999.999": 180
  },
  {
    "1": 405,
    "Blue-eyes White Dragon": "Saber Slasher",
    "999.999": 180
  },
  {
    "1": 406,
    "Blue-eyes White Dragon": "Yaiba Robo",
    "999.999": 80
  },
  {
    "1": 407,
    "Blue-eyes White Dragon": "Machine King",
    "999.999": 800
  },
  {
    "1": 408,
    "Blue-eyes White Dragon": "Giant Mech-soldier",
    "999.999": 400
  },
  {
    "1": 409,
    "Blue-eyes White Dragon": "Metal Dragon",
    "999.999": 350
  },
  {
    "1": 410,
    "Blue-eyes White Dragon": "Mechanical Spider",
    "999.999": 20
  },
  {
    "1": 411,
    "Blue-eyes White Dragon": "Bat",
    "999.999": 15
  },
  {
    "1": 412,
    "Blue-eyes White Dragon": "Giga-tech Wolf",
    "999.999": 120
  },
  {
    "1": 413,
    "Blue-eyes White Dragon": "Cyber Soldier",
    "999.999": 260
  },
  {
    "1": 414,
    "Blue-eyes White Dragon": "Shovel Crusher",
    "999.999": 60
  },
  {
    "1": 415,
    "Blue-eyes White Dragon": "Mechanicalchacer",
    "999.999": 120
  },
  {
    "1": 416,
    "Blue-eyes White Dragon": "Blocker",
    "999.999": 120
  },
  {
    "1": 417,
    "Blue-eyes White Dragon": "Blast Juggler",
    "999.999": 40
  },
  {
    "1": 418,
    "Blue-eyes White Dragon": "Golgoil",
    "999.999": 100
  },
  {
    "1": 419,
    "Blue-eyes White Dragon": "Giganto",
    "999.999": 350
  },
  {
    "1": 420,
    "Blue-eyes White Dragon": "Cyber-Stein",
    "999.999": 25
  },
  {
    "1": 421,
    "Blue-eyes White Dragon": "Cyber Commander",
    "999.999": 30
  },
  {
    "1": 422,
    "Blue-eyes White Dragon": "Jinzo #7",
    "999.999": 20
  },
  {
    "1": 423,
    "Blue-eyes White Dragon": "Dice Armadillo",
    "999.999": 320
  },
  {
    "1": 424,
    "Blue-eyes White Dragon": "Sky Dragon",
    "999.999": 1
  },
  {
    "1": 425,
    "Blue-eyes White Dragon": "Thunder Dragon",
    "999.999": 230
  },
  {
    "1": 426,
    "Blue-eyes White Dragon": "Stone D.",
    "999.999": 900
  },
  {
    "1": 427,
    "Blue-eyes White Dragon": "Kaiser Dragon",
    "999.999": 900
  },
  {
    "1": 428,
    "Blue-eyes White Dragon": "Magician of Faith",
    "999.999": 999.999
  },
  {
    "1": 429,
    "Blue-eyes White Dragon": "Goddess of Whim",
    "999.999": 999.999
  },
  {
    "1": 430,
    "Blue-eyes White Dragon": "Water Magician",
    "999.999": 120
  },
  {
    "1": 431,
    "Blue-eyes White Dragon": "Ice Water",
    "999.999": 55
  },
  {
    "1": 432,
    "Blue-eyes White Dragon": "Waterdragon Fairy",
    "999.999": 45
  },
  {
    "1": 433,
    "Blue-eyes White Dragon": "Ancient Elf",
    "999.999": 120
  },
  {
    "1": 434,
    "Blue-eyes White Dragon": "Beautiful Beast Trainer",
    "999.999": 260
  },
  {
    "1": 435,
    "Blue-eyes White Dragon": "Water Girl",
    "999.999": 70
  },
  {
    "1": 436,
    "Blue-eyes White Dragon": "White Dolphin",
    "999.999": 20
  },
  {
    "1": 437,
    "Blue-eyes White Dragon": "Deepsea Shark",
    "999.999": 350
  },
  {
    "1": 438,
    "Blue-eyes White Dragon": "Metal Fish",
    "999.999": 350
  },
  {
    "1": 439,
    "Blue-eyes White Dragon": "Bottom Dweller",
    "999.999": 290
  },
  {
    "1": 440,
    "Blue-eyes White Dragon": "7 Colored Fish",
    "999.999": 120
  },
  {
    "1": 441,
    "Blue-eyes White Dragon": "Mech Bass",
    "999.999": 290
  },
  {
    "1": 442,
    "Blue-eyes White Dragon": "Aqua Dragon",
    "999.999": 700
  },
  {
    "1": 443,
    "Blue-eyes White Dragon": "Sea King Dragon",
    "999.999": 1
  },
  {
    "1": 444,
    "Blue-eyes White Dragon": "Turu-Purun",
    "999.999": 20
  },
  {
    "1": 445,
    "Blue-eyes White Dragon": "Guardian of the Sea",
    "999.999": 80
  },
  {
    "1": 446,
    "Blue-eyes White Dragon": "Aqua Snake",
    "999.999": 50
  },
  {
    "1": 447,
    "Blue-eyes White Dragon": "Giant Red Seasnake",
    "999.999": 120
  },
  {
    "1": 448,
    "Blue-eyes White Dragon": "Spike Seadra",
    "999.999": 180
  },
  {
    "1": 449,
    "Blue-eyes White Dragon": "30,000-Year White Turtle",
    "999.999": 290
  },
  {
    "1": 450,
    "Blue-eyes White Dragon": "Kappa Avenger",
    "999.999": 60
  },
  {
    "1": 451,
    "Blue-eyes White Dragon": "Kanikabuto",
    "999.999": 30
  },
  {
    "1": 452,
    "Blue-eyes White Dragon": "Zarigun",
    "999.999": 30
  },
  {
    "1": 453,
    "Blue-eyes White Dragon": "Millennium Golem",
    "999.999": 800
  },
  {
    "1": 454,
    "Blue-eyes White Dragon": "Destroyer Golem",
    "999.999": 100
  },
  {
    "1": 455,
    "Blue-eyes White Dragon": "Barrel Rock",
    "999.999": 80
  },
  {
    "1": 456,
    "Blue-eyes White Dragon": "Minomushi Warrior",
    "999.999": 100
  },
  {
    "1": 457,
    "Blue-eyes White Dragon": "Stone Ghost",
    "999.999": 70
  },
  {
    "1": 458,
    "Blue-eyes White Dragon": "Kaminari Attack",
    "999.999": 290
  },
  {
    "1": 459,
    "Blue-eyes White Dragon": "Tripwire Beast",
    "999.999": 100
  },
  {
    "1": 460,
    "Blue-eyes White Dragon": "Bolt Escargot",
    "999.999": 180
  },
  {
    "1": 461,
    "Blue-eyes White Dragon": "Bolt Penguin",
    "999.999": 50
  },
  {
    "1": 462,
    "Blue-eyes White Dragon": "The Immortal of Thunder",
    "999.999": 160
  },
  {
    "1": 463,
    "Blue-eyes White Dragon": "Electric Snake",
    "999.999": 40
  },
  {
    "1": 464,
    "Blue-eyes White Dragon": "Wing Eagle",
    "999.999": 290
  },
  {
    "1": 465,
    "Blue-eyes White Dragon": "Punished Eagle",
    "999.999": 550
  },
  {
    "1": 466,
    "Blue-eyes White Dragon": "Skull Red Bird",
    "999.999": 140
  },
  {
    "1": 467,
    "Blue-eyes White Dragon": "Crimson Sunbird",
    "999.999": 700
  },
  {
    "1": 468,
    "Blue-eyes White Dragon": "Queen Bird",
    "999.999": 260
  },
  {
    "1": 469,
    "Blue-eyes White Dragon": "Armed Ninja",
    "999.999": 15
  },
  {
    "1": 470,
    "Blue-eyes White Dragon": "Magical Ghost",
    "999.999": 140
  },
  {
    "1": 471,
    "Blue-eyes White Dragon": "Soul Hunter",
    "999.999": 800
  },
  {
    "1": 472,
    "Blue-eyes White Dragon": "Air Eater",
    "999.999": 1
  },
  {
    "1": 473,
    "Blue-eyes White Dragon": "Vermillion Sparrow",
    "999.999": 320
  },
  {
    "1": 474,
    "Blue-eyes White Dragon": "Sea Kamen",
    "999.999": 120
  },
  {
    "1": 475,
    "Blue-eyes White Dragon": "Sinister Serpent",
    "999.999": 10
  },
  {
    "1": 476,
    "Blue-eyes White Dragon": "Ganigumo",
    "999.999": 30
  },
  {
    "1": 477,
    "Blue-eyes White Dragon": "Alinsection",
    "999.999": 35
  },
  {
    "1": 478,
    "Blue-eyes White Dragon": "Insect Soldiers of the Sky",
    "999.999": 45
  },
  {
    "1": 479,
    "Blue-eyes White Dragon": "Cockroach Knight",
    "999.999": 999.999
  },
  {
    "1": 480,
    "Blue-eyes White Dragon": "Kuwagata α",
    "999.999": 70
  },
  {
    "1": 481,
    "Blue-eyes White Dragon": "Burglar",
    "999.999": 35
  },
  {
    "1": 482,
    "Blue-eyes White Dragon": "Pragtical",
    "999.999": 320
  },
  {
    "1": 483,
    "Blue-eyes White Dragon": "Garvas",
    "999.999": 1
  },
  {
    "1": 484,
    "Blue-eyes White Dragon": "Ameba",
    "999.999": 15
  },
  {
    "1": 485,
    "Blue-eyes White Dragon": "Korogashi",
    "999.999": 20
  },
  {
    "1": 486,
    "Blue-eyes White Dragon": "Boo Koo",
    "999.999": 25
  },
  {
    "1": 487,
    "Blue-eyes White Dragon": "Flower Wolf",
    "999.999": 260
  },
  {
    "1": 488,
    "Blue-eyes White Dragon": "Rainbow Flower",
    "999.999": 20
  },
  {
    "1": 489,
    "Blue-eyes White Dragon": "Barrel Lily",
    "999.999": 40
  },
  {
    "1": 490,
    "Blue-eyes White Dragon": "Needle Ball",
    "999.999": 30
  },
  {
    "1": 491,
    "Blue-eyes White Dragon": "Peacock",
    "999.999": 260
  },
  {
    "1": 492,
    "Blue-eyes White Dragon": "Hoshiningen",
    "999.999": 25
  },
  {
    "1": 493,
    "Blue-eyes White Dragon": "Maha Vailo",
    "999.999": 180
  },
  {
    "1": 494,
    "Blue-eyes White Dragon": "Rainbow Marine Mermaid",
    "999.999": 260
  },
  {
    "1": 495,
    "Blue-eyes White Dragon": "Musician King",
    "999.999": 260
  },
  {
    "1": 496,
    "Blue-eyes White Dragon": "Wilmee",
    "999.999": 70
  },
  {
    "1": 497,
    "Blue-eyes White Dragon": "Yado Karu",
    "999.999": 120
  },
  {
    "1": 498,
    "Blue-eyes White Dragon": "Morinphen",
    "999.999": 160
  },
  {
    "1": 499,
    "Blue-eyes White Dragon": "Kattapillar",
    "999.999": 999.999
  },
  {
    "1": 500,
    "Blue-eyes White Dragon": "Dragon Seeker",
    "999.999": 700
  },
  {
    "1": 501,
    "Blue-eyes White Dragon": "Man-eater Bug",
    "999.999": 20
  },
  {
    "1": 502,
    "Blue-eyes White Dragon": "D. Human",
    "999.999": 120
  },
  {
    "1": 503,
    "Blue-eyes White Dragon": "Turtle Raccoon",
    "999.999": 35
  },
  {
    "1": 504,
    "Blue-eyes White Dragon": "Fungi of the Musk",
    "999.999": 15
  },
  {
    "1": 505,
    "Blue-eyes White Dragon": "Prisman",
    "999.999": 45
  },
  {
    "1": 506,
    "Blue-eyes White Dragon": "Gale Dogra",
    "999.999": 25
  },
  {
    "1": 507,
    "Blue-eyes White Dragon": "Crazy Fish",
    "999.999": 160
  },
  {
    "1": 508,
    "Blue-eyes White Dragon": "Cyber Saurus",
    "999.999": 260
  },
  {
    "1": 509,
    "Blue-eyes White Dragon": "Bracchio-raidus",
    "999.999": 800
  },
  {
    "1": 510,
    "Blue-eyes White Dragon": "Laughing Flower",
    "999.999": 30
  },
  {
    "1": 511,
    "Blue-eyes White Dragon": "Bean Soldier",
    "999.999": 140
  },
  {
    "1": 512,
    "Blue-eyes White Dragon": "Cannon Soldier",
    "999.999": 140
  },
  {
    "1": 513,
    "Blue-eyes White Dragon": "Guardian of the Throne Room",
    "999.999": 260
  },
  {
    "1": 514,
    "Blue-eyes White Dragon": "Brave Scizzar",
    "999.999": 80
  },
  {
    "1": 515,
    "Blue-eyes White Dragon": "The Statue of Easter Island",
    "999.999": 100
  },
  {
    "1": 516,
    "Blue-eyes White Dragon": "Muka Muka",
    "999.999": 20
  },
  {
    "1": 517,
    "Blue-eyes White Dragon": "Sand Stone",
    "999.999": 180
  },
  {
    "1": 518,
    "Blue-eyes White Dragon": "Boulder Tortoise",
    "999.999": 400
  },
  {
    "1": 519,
    "Blue-eyes White Dragon": "Fire Kraken",
    "999.999": 230
  },
  {
    "1": 520,
    "Blue-eyes White Dragon": "Turtle Bird",
    "999.999": 400
  },
  {
    "1": 521,
    "Blue-eyes White Dragon": "Skullbird",
    "999.999": 400
  },
  {
    "1": 522,
    "Blue-eyes White Dragon": "Monstrous Bird",
    "999.999": 550
  },
  {
    "1": 523,
    "Blue-eyes White Dragon": "The Bistro Butcher",
    "999.999": 160
  },
  {
    "1": 524,
    "Blue-eyes White Dragon": "Star Boy",
    "999.999": 20
  },
  {
    "1": 525,
    "Blue-eyes White Dragon": "Spirit of the Mountain",
    "999.999": 230
  },
  {
    "1": 526,
    "Blue-eyes White Dragon": "Neck Hunter",
    "999.999": 400
  },
  {
    "1": 527,
    "Blue-eyes White Dragon": "Milus Radiant",
    "999.999": 10
  },
  {
    "1": 528,
    "Blue-eyes White Dragon": "Togex",
    "999.999": 320
  },
  {
    "1": 529,
    "Blue-eyes White Dragon": "Flame Cerebrus",
    "999.999": 550
  },
  {
    "1": 530,
    "Blue-eyes White Dragon": "Eldeen",
    "999.999": 50
  },
  {
    "1": 531,
    "Blue-eyes White Dragon": "Mystical Sand",
    "999.999": 500
  },
  {
    "1": 532,
    "Blue-eyes White Dragon": "Gemini Elf",
    "999.999": 160
  },
  {
    "1": 533,
    "Blue-eyes White Dragon": "Kwagar Hercules",
    "999.999": 400
  },
  {
    "1": 534,
    "Blue-eyes White Dragon": "Minar",
    "999.999": 35
  },
  {
    "1": 535,
    "Blue-eyes White Dragon": "Kamakiriman",
    "999.999": 100
  },
  {
    "1": 536,
    "Blue-eyes White Dragon": "Mechaleon",
    "999.999": 30
  },
  {
    "1": 537,
    "Blue-eyes White Dragon": "Mega Thunderball",
    "999.999": 30
  },
  {
    "1": 538,
    "Blue-eyes White Dragon": "Niwatori",
    "999.999": 40
  },
  {
    "1": 539,
    "Blue-eyes White Dragon": "Corroding Shark",
    "999.999": 45
  },
  {
    "1": 540,
    "Blue-eyes White Dragon": "Skelengel",
    "999.999": 30
  },
  {
    "1": 541,
    "Blue-eyes White Dragon": "Hane-Hane",
    "999.999": 999.999
  },
  {
    "1": 542,
    "Blue-eyes White Dragon": "Misairuzame",
    "999.999": 200
  },
  {
    "1": 543,
    "Blue-eyes White Dragon": "Tongyo",
    "999.999": 60
  },
  {
    "1": 544,
    "Blue-eyes White Dragon": "Dharma Cannon",
    "999.999": 30
  },
  {
    "1": 545,
    "Blue-eyes White Dragon": "Skelgon",
    "999.999": 999.999
  },
  {
    "1": 546,
    "Blue-eyes White Dragon": "Wow Warrior",
    "999.999": 60
  },
  {
    "1": 547,
    "Blue-eyes White Dragon": "Griggle",
    "999.999": 15
  },
  {
    "1": 548,
    "Blue-eyes White Dragon": "Bone Mouse",
    "999.999": 15
  },
  {
    "1": 549,
    "Blue-eyes White Dragon": "Frog The Jam",
    "999.999": 25
  },
  {
    "1": 550,
    "Blue-eyes White Dragon": "Behegon",
    "999.999": 80
  },
  {
    "1": 551,
    "Blue-eyes White Dragon": "Dark Elf",
    "999.999": 160
  },
  {
    "1": 552,
    "Blue-eyes White Dragon": "Winged Dragon #2",
    "999.999": 70
  },
  {
    "1": 553,
    "Blue-eyes White Dragon": "Mushroom Man #2",
    "999.999": 55
  },
  {
    "1": 554,
    "Blue-eyes White Dragon": "Lava Battleguard",
    "999.999": 999.999
  },
  {
    "1": 555,
    "Blue-eyes White Dragon": "Tyhone #2",
    "999.999": 999.999
  },
  {
    "1": 556,
    "Blue-eyes White Dragon": "The Wandering Doomed",
    "999.999": 30
  },
  {
    "1": 557,
    "Blue-eyes White Dragon": "Steel Ogre Grotto #1",
    "999.999": 260
  },
  {
    "1": 558,
    "Blue-eyes White Dragon": "Pot the Trick",
    "999.999": 20
  },
  {
    "1": 559,
    "Blue-eyes White Dragon": "Oscillo Hero",
    "999.999": 50
  },
  {
    "1": 560,
    "Blue-eyes White Dragon": "Invader from Another Dimension",
    "999.999": 80
  },
  {
    "1": 561,
    "Blue-eyes White Dragon": "Lesser Dragon",
    "999.999": 70
  },
  {
    "1": 562,
    "Blue-eyes White Dragon": "Needle Worm",
    "999.999": 999.999
  },
  {
    "1": 563,
    "Blue-eyes White Dragon": "Wretched Ghost of the Attic",
    "999.999": 20
  },
  {
    "1": 564,
    "Blue-eyes White Dragon": "Great Mammoth of Goldfine",
    "999.999": 800
  },
  {
    "1": 565,
    "Blue-eyes White Dragon": "Man-eating Black Shark",
    "999.999": 320
  },
  {
    "1": 566,
    "Blue-eyes White Dragon": "Yormungarde",
    "999.999": 60
  },
  {
    "1": 567,
    "Blue-eyes White Dragon": "Darkworld Thorns",
    "999.999": 60
  },
  {
    "1": 568,
    "Blue-eyes White Dragon": "Anthrosaurus",
    "999.999": 45
  },
  {
    "1": 569,
    "Blue-eyes White Dragon": "Drooling Lizard",
    "999.999": 40
  },
  {
    "1": 570,
    "Blue-eyes White Dragon": "Trakadon",
    "999.999": 60
  },
  {
    "1": 571,
    "Blue-eyes White Dragon": "B. Dragon Jungle King",
    "999.999": 999.999
  },
  {
    "1": 572,
    "Blue-eyes White Dragon": "Empress Judge",
    "999.999": 500
  },
  {
    "1": 573,
    "Blue-eyes White Dragon": "Little D",
    "999.999": 45
  },
  {
    "1": 574,
    "Blue-eyes White Dragon": "Witch of the Black Forest",
    "999.999": 80
  },
  {
    "1": 575,
    "Blue-eyes White Dragon": "Ancient One of the Deep Forest",
    "999.999": 1
  },
  {
    "1": 576,
    "Blue-eyes White Dragon": "Giant Scorpion of the Tundra",
    "999.999": 60
  },
  {
    "1": 577,
    "Blue-eyes White Dragon": "Crow Goblin",
    "999.999": 320
  },
  {
    "1": 578,
    "Blue-eyes White Dragon": "Leo Wizard",
    "999.999": 100
  },
  {
    "1": 579,
    "Blue-eyes White Dragon": "Abyss Flower",
    "999.999": 25
  },
  {
    "1": 580,
    "Blue-eyes White Dragon": "Patrol Robo",
    "999.999": 55
  },
  {
    "1": 581,
    "Blue-eyes White Dragon": "Takuhee",
    "999.999": 120
  },
  {
    "1": 582,
    "Blue-eyes White Dragon": "Dark Witch",
    "999.999": 350
  },
  {
    "1": 583,
    "Blue-eyes White Dragon": "Weather Report",
    "999.999": 120
  },
  {
    "1": 584,
    "Blue-eyes White Dragon": "Binding Chain",
    "999.999": 60
  },
  {
    "1": 585,
    "Blue-eyes White Dragon": "Mechanical Snail",
    "999.999": 45
  },
  {
    "1": 586,
    "Blue-eyes White Dragon": "Greenkappa",
    "999.999": 30
  },
  {
    "1": 587,
    "Blue-eyes White Dragon": "Mon Larvas",
    "999.999": 140
  },
  {
    "1": 588,
    "Blue-eyes White Dragon": "Living Vase",
    "999.999": 55
  },
  {
    "1": 589,
    "Blue-eyes White Dragon": "Tentacle Plant",
    "999.999": 25
  },
  {
    "1": 590,
    "Blue-eyes White Dragon": "Beaked Snake",
    "999.999": 40
  },
  {
    "1": 591,
    "Blue-eyes White Dragon": "Morphing Jar",
    "999.999": 30
  },
  {
    "1": 592,
    "Blue-eyes White Dragon": "Muse-A",
    "999.999": 40
  },
  {
    "1": 593,
    "Blue-eyes White Dragon": "Giant Turtle Who Feeds on Flames",
    "999.999": 260
  },
  {
    "1": 594,
    "Blue-eyes White Dragon": "Rose Spectre of Dunn",
    "999.999": 500
  },
  {
    "1": 595,
    "Blue-eyes White Dragon": "Fiend Refrection #1",
    "999.999": 140
  },
  {
    "1": 596,
    "Blue-eyes White Dragon": "Ghoul with an Appetite",
    "999.999": 160
  },
  {
    "1": 597,
    "Blue-eyes White Dragon": "Pale Beast",
    "999.999": 140
  },
  {
    "1": 598,
    "Blue-eyes White Dragon": "Little Chimera",
    "999.999": 25
  },
  {
    "1": 599,
    "Blue-eyes White Dragon": "Violent Rain",
    "999.999": 80
  },
  {
    "1": 600,
    "Blue-eyes White Dragon": "Key Mace #2",
    "999.999": 70
  },
  {
    "1": 601,
    "Blue-eyes White Dragon": "Tenderness",
    "999.999": 60
  },
  {
    "1": 602,
    "Blue-eyes White Dragon": "Penguin Soldier",
    "999.999": 25
  },
  {
    "1": 603,
    "Blue-eyes White Dragon": "Fairy Dragon",
    "999.999": 999.999
  },
  {
    "1": 604,
    "Blue-eyes White Dragon": "Obese Marmot of Nefariousness",
    "999.999": 30
  },
  {
    "1": 605,
    "Blue-eyes White Dragon": "Liquid Beast",
    "999.999": 40
  },
  {
    "1": 606,
    "Blue-eyes White Dragon": "Twin Long Rods #2",
    "999.999": 30
  },
  {
    "1": 607,
    "Blue-eyes White Dragon": "Great Bill",
    "999.999": 100
  },
  {
    "1": 608,
    "Blue-eyes White Dragon": "Shining Friendship",
    "999.999": 120
  },
  {
    "1": 609,
    "Blue-eyes White Dragon": "Bladefly",
    "999.999": 30
  },
  {
    "1": 610,
    "Blue-eyes White Dragon": "Electric Lizard",
    "999.999": 35
  },
  {
    "1": 611,
    "Blue-eyes White Dragon": "Hiro's Shadow Scout",
    "999.999": 25
  },
  {
    "1": 612,
    "Blue-eyes White Dragon": "Lady of Faith",
    "999.999": 50
  },
  {
    "1": 613,
    "Blue-eyes White Dragon": "Twin-headed Thunder Dragon",
    "999.999": 1.9
  },
  {
    "1": 614,
    "Blue-eyes White Dragon": "Hunter Spider",
    "999.999": 200
  },
  {
    "1": 615,
    "Blue-eyes White Dragon": "Armored Starfish",
    "999.999": 70
  },
  {
    "1": 616,
    "Blue-eyes White Dragon": "Hourglass of Courage",
    "999.999": 80
  },
  {
    "1": 617,
    "Blue-eyes White Dragon": "Marine Beast",
    "999.999": 290
  },
  {
    "1": 618,
    "Blue-eyes White Dragon": "Warrior of Tradition",
    "999.999": 400
  },
  {
    "1": 619,
    "Blue-eyes White Dragon": "Rock Spirit",
    "999.999": 350
  },
  {
    "1": 620,
    "Blue-eyes White Dragon": "Snakeyashi",
    "999.999": 70
  },
  {
    "1": 621,
    "Blue-eyes White Dragon": "Succubus Knight",
    "999.999": 180
  },
  {
    "1": 622,
    "Blue-eyes White Dragon": "Ill Witch",
    "999.999": 230
  },
  {
    "1": 623,
    "Blue-eyes White Dragon": "The Thing That Hides In the Mud",
    "999.999": 100
  },
  {
    "1": 624,
    "Blue-eyes White Dragon": "High Tide Gyojin",
    "999.999": 180
  },
  {
    "1": 625,
    "Blue-eyes White Dragon": "Fairy of the Fountain",
    "999.999": 140
  },
  {
    "1": 626,
    "Blue-eyes White Dragon": "Amazon of the Seas",
    "999.999": 140
  },
  {
    "1": 627,
    "Blue-eyes White Dragon": "Nekogal #2",
    "999.999": 550
  },
  {
    "1": 628,
    "Blue-eyes White Dragon": "Witch's Apprentice",
    "999.999": 999.999
  },
  {
    "1": 629,
    "Blue-eyes White Dragon": "Armored Rat",
    "999.999": 55
  },
  {
    "1": 630,
    "Blue-eyes White Dragon": "Ancient Lizard Warrior",
    "999.999": 100
  },
  {
    "1": 631,
    "Blue-eyes White Dragon": "Maiden of the Moonlight",
    "999.999": 160
  },
  {
    "1": 632,
    "Blue-eyes White Dragon": "Stone Ogre Grotto",
    "999.999": 230
  },
  {
    "1": 633,
    "Blue-eyes White Dragon": "Winged Egg of New Life",
    "999.999": 230
  },
  {
    "1": 634,
    "Blue-eyes White Dragon": "Night Lizard",
    "999.999": 120
  },
  {
    "1": 635,
    "Blue-eyes White Dragon": "Queen's Double",
    "999.999": 15
  },
  {
    "1": 636,
    "Blue-eyes White Dragon": "Blue-winged Crown",
    "999.999": 160
  },
  {
    "1": 637,
    "Blue-eyes White Dragon": "Trent",
    "999.999": 290
  },
  {
    "1": 638,
    "Blue-eyes White Dragon": "Queen of Autumn Leaves",
    "999.999": 290
  },
  {
    "1": 639,
    "Blue-eyes White Dragon": "Amphibious Bugroth",
    "999.999": 230
  },
  {
    "1": 640,
    "Blue-eyes White Dragon": "Acid Crawler",
    "999.999": 999.999
  },
  {
    "1": 641,
    "Blue-eyes White Dragon": "Invader of the Throne",
    "999.999": 200
  },
  {
    "1": 642,
    "Blue-eyes White Dragon": "Mystical Sheep #1",
    "999.999": 55
  },
  {
    "1": 643,
    "Blue-eyes White Dragon": "Disk Magician",
    "999.999": 80
  },
  {
    "1": 644,
    "Blue-eyes White Dragon": "Flame Viper",
    "999.999": 20
  },
  {
    "1": 645,
    "Blue-eyes White Dragon": "Royal Guard",
    "999.999": 700
  },
  {
    "1": 646,
    "Blue-eyes White Dragon": "Gruesome Goo",
    "999.999": 55
  },
  {
    "1": 647,
    "Blue-eyes White Dragon": "Hyosube",
    "999.999": 120
  },
  {
    "1": 648,
    "Blue-eyes White Dragon": "Machine Attacker",
    "999.999": 180
  },
  {
    "1": 649,
    "Blue-eyes White Dragon": "Hibikime",
    "999.999": 120
  },
  {
    "1": 650,
    "Blue-eyes White Dragon": "Whiptail Crow",
    "999.999": 260
  },
  {
    "1": 651,
    "Blue-eyes White Dragon": "Kunai with Chain",
    "999.999": 800
  },
  {
    "1": 652,
    "Blue-eyes White Dragon": "Magical Labyrinth",
    "999.999": 10
  },
  {
    "1": 653,
    "Blue-eyes White Dragon": "Warrior Elimination",
    "999.999": 999.999
  },
  {
    "1": 654,
    "Blue-eyes White Dragon": "Salamandra",
    "999.999": 800
  },
  {
    "1": 655,
    "Blue-eyes White Dragon": "Cursebreaker",
    "999.999": 10
  },
  {
    "1": 656,
    "Blue-eyes White Dragon": "Eternal Rest",
    "999.999": 999.999
  },
  {
    "1": 657,
    "Blue-eyes White Dragon": "Megamorph",
    "999.999": 50
  },
  {
    "1": 658,
    "Blue-eyes White Dragon": "Metalmorph",
    "999.999": 999.999
  },
  {
    "1": 659,
    "Blue-eyes White Dragon": "Winged Trumpeter",
    "999.999": 800
  },
  {
    "1": 660,
    "Blue-eyes White Dragon": "Stain Storm",
    "999.999": 999.999
  },
  {
    "1": 661,
    "Blue-eyes White Dragon": "Crush Card",
    "999.999": 999.999
  },
  {
    "1": 662,
    "Blue-eyes White Dragon": "Eradicating Aerosol",
    "999.999": 999.999
  },
  {
    "1": 663,
    "Blue-eyes White Dragon": "Breath of Light",
    "999.999": 999.999
  },
  {
    "1": 664,
    "Blue-eyes White Dragon": "Eternal Draught",
    "999.999": 999.999
  },
  {
    "1": 665,
    "Blue-eyes White Dragon": "Curse of Millennium Shield",
    "999.999": 10
  },
  {
    "1": 666,
    "Blue-eyes White Dragon": "Yamadron Ritual",
    "999.999": 10
  },
  {
    "1": 667,
    "Blue-eyes White Dragon": "Gate Guardian Ritual",
    "999.999": 999.999
  },
  {
    "1": 668,
    "Blue-eyes White Dragon": "Bright Castle",
    "999.999": 800
  },
  {
    "1": 669,
    "Blue-eyes White Dragon": "Shadow Spell",
    "999.999": 999.999
  },
  {
    "1": 670,
    "Blue-eyes White Dragon": "Black Luster Ritual",
    "999.999": 100
  },
  {
    "1": 671,
    "Blue-eyes White Dragon": "Zera Ritual",
    "999.999": 100
  },
  {
    "1": 672,
    "Blue-eyes White Dragon": "Harpie's Feather Duster",
    "999.999": 999.999
  },
  {
    "1": 673,
    "Blue-eyes White Dragon": "War-lion Ritual",
    "999.999": 100
  },
  {
    "1": 674,
    "Blue-eyes White Dragon": "Beastry Mirror Ritual",
    "999.999": 100
  },
  {
    "1": 675,
    "Blue-eyes White Dragon": "Ultimate Dragon",
    "999.999": 999.999
  },
  {
    "1": 676,
    "Blue-eyes White Dragon": "Commencement Dance",
    "999.999": 50
  },
  {
    "1": 677,
    "Blue-eyes White Dragon": "Hamburger Recipe",
    "999.999": 50
  },
  {
    "1": 678,
    "Blue-eyes White Dragon": "Revival of Sennen Genjin",
    "999.999": 100
  },
  {
    "1": 679,
    "Blue-eyes White Dragon": "Novox's Prayer",
    "999.999": 50
  },
  {
    "1": 680,
    "Blue-eyes White Dragon": "Curse of Tri-Horned Dragon",
    "999.999": 50
  },
  {
    "1": 681,
    "Blue-eyes White Dragon": "House of Adhesive Tape",
    "999.999": 999.999
  },
  {
    "1": 682,
    "Blue-eyes White Dragon": "Eatgaboon",
    "999.999": 999.999
  },
  {
    "1": 683,
    "Blue-eyes White Dragon": "Bear Trap",
    "999.999": 999.999
  },
  {
    "1": 684,
    "Blue-eyes White Dragon": "Invisible Wire",
    "999.999": 999.999
  },
  {
    "1": 685,
    "Blue-eyes White Dragon": "Acid Trap Hole",
    "999.999": 999.999
  },
  {
    "1": 686,
    "Blue-eyes White Dragon": "Widespread Ruin",
    "999.999": 999.999
  },
  {
    "1": 687,
    "Blue-eyes White Dragon": "Goblin Fan",
    "999.999": 999.999
  },
  {
    "1": 688,
    "Blue-eyes White Dragon": "Bad Reaction to Simochi",
    "999.999": 999.999
  },
  {
    "1": 689,
    "Blue-eyes White Dragon": "Reverse Trap",
    "999.999": 999.999
  },
  {
    "1": 690,
    "Blue-eyes White Dragon": "Fake Trap",
    "999.999": 999.999
  },
  {
    "1": 691,
    "Blue-eyes White Dragon": "Revived of Serpent Night Dragon",
    "999.999": 50
  },
  {
    "1": 692,
    "Blue-eyes White Dragon": "Turtle Oath",
    "999.999": 100
  },
  {
    "1": 693,
    "Blue-eyes White Dragon": "Contruct of Mask",
    "999.999": 100
  },
  {
    "1": 694,
    "Blue-eyes White Dragon": "Resurrection of Chakra",
    "999.999": 100
  },
  {
    "1": 695,
    "Blue-eyes White Dragon": "Puppet Ritual",
    "999.999": 50
  },
  {
    "1": 696,
    "Blue-eyes White Dragon": "Javelin Beetle Pact",
    "999.999": 999.999
  },
  {
    "1": 697,
    "Blue-eyes White Dragon": "Garma Sword Oath",
    "999.999": 50
  },
  {
    "1": 698,
    "Blue-eyes White Dragon": "Cosmo Queen's Prayer",
    "999.999": 50
  },
  {
    "1": 699,
    "Blue-eyes White Dragon": "Revival of Skeleton Rider",
    "999.999": 10
  },
  {
    "1": 700,
    "Blue-eyes White Dragon": "Fortress Whale's Oath",
    "999.999": 10
  },
  {
    "1": 701,
    "Blue-eyes White Dragon": "Performance of Sword",
    "999.999": ""
  },
  {
    "1": 702,
    "Blue-eyes White Dragon": "Hungry Burger",
    "999.999": ""
  },
  {
    "1": 703,
    "Blue-eyes White Dragon": "Sengenjin",
    "999.999": ""
  },
  {
    "1": 704,
    "Blue-eyes White Dragon": "Skull Guardian",
    "999.999": ""
  },
  {
    "1": 705,
    "Blue-eyes White Dragon": "Tri-horned Dragon",
    "999.999": ""
  },
  {
    "1": 706,
    "Blue-eyes White Dragon": "Serpent Night Dragon",
    "999.999": ""
  },
  {
    "1": 707,
    "Blue-eyes White Dragon": "Skull Knight",
    "999.999": 999.999
  },
  {
    "1": 708,
    "Blue-eyes White Dragon": "Cosmo Queen",
    "999.999": ""
  },
  {
    "1": 709,
    "Blue-eyes White Dragon": "Chakra",
    "999.999": ""
  },
  {
    "1": 710,
    "Blue-eyes White Dragon": "Crab Turtle",
    "999.999": ""
  },
  {
    "1": 711,
    "Blue-eyes White Dragon": "Mikazukinoyaiba",
    "999.999": 999.999
  },
  {
    "1": 712,
    "Blue-eyes White Dragon": "Meteor Dragon",
    "999.999": 999.999
  },
  {
    "1": 713,
    "Blue-eyes White Dragon": "Meteor B. Dragon",
    "999.999": ""
  },
  {
    "1": 714,
    "Blue-eyes White Dragon": "Firewing Pegasus",
    "999.999": 999.999
  },
  {
    "1": 715,
    "Blue-eyes White Dragon": "Psycho-Puppet",
    "999.999": ""
  },
  {
    "1": 716,
    "Blue-eyes White Dragon": "Garma Sword",
    "999.999": ""
  },
  {
    "1": 717,
    "Blue-eyes White Dragon": "Javelin Beetle",
    "999.999": ""
  },
  {
    "1": 718,
    "Blue-eyes White Dragon": "Fortress Whale",
    "999.999": ""
  },
  {
    "1": 719,
    "Blue-eyes White Dragon": "Dokurorider",
    "999.999": ""
  },
  {
    "1": 720,
    "Blue-eyes White Dragon": "Mask of Shine & Dark",
    "999.999": ""
  },
  {
    "1": 721,
    "Blue-eyes White Dragon": "Dark Magic Ritual",
    "999.999": ""
  },
  {
    "1": 722,
    "Blue-eyes White Dragon": "Magician of Black Chaos",
    "999.999": ""
  }
]